iranholidays/__init__.py
iranholidays-0.2.4.dist-info/LICENSE
iranholidays-0.2.4.dist-info/WHEEL
iranholidays-0.2.4.dist-info/METADATA
iranholidays-0.2.4.dist-info/RECORD
