Metadata-Version: 2.1
Name: iranholidays
Version: 0.2.4
Summary: provides functions to tell if a date is a holiday in Iran or not
Author-email: 5j9 <5j9@users.noreply.github.com>
Requires-Python: >=3.11
Requires-Dist: gshconverter
Requires-Dist: hijri-converter
Project-URL: Homepage, https://github.com/5j9/iranholidays
